pyknp_eventgraph/__init__.py
pyknp_eventgraph/argument.py
pyknp_eventgraph/base_phrase.py
pyknp_eventgraph/builder.py
pyknp_eventgraph/cli.py
pyknp_eventgraph/component.py
pyknp_eventgraph/document.py
pyknp_eventgraph/event.py
pyknp_eventgraph/eventgraph.py
pyknp_eventgraph/features.py
pyknp_eventgraph/helper.py
pyknp_eventgraph/pas.py
pyknp_eventgraph/predicate.py
pyknp_eventgraph/relation.py
pyknp_eventgraph/sentence.py
pyknp_eventgraph/utils.py
pyknp_eventgraph/visualizer.py
pyknp_eventgraph-6.2.5.dist-info/entry_points.txt
pyknp_eventgraph-6.2.5.dist-info/LICENSE
pyknp_eventgraph-6.2.5.dist-info/WHEEL
pyknp_eventgraph-6.2.5.dist-info/METADATA
pyknp_eventgraph-6.2.5.dist-info/RECORD
