Metadata-Version: 2.1
Name: pyknp-eventgraph
Version: 6.2.5
Summary: A development platform for high-level NLP applications in Japanese
Home-page: https://github.com/ku-nlp/pyknp-eventgraph
License: BSD-3-Clause
Keywords: NLP,JUMAN,KNP
Author: Hirokazu Kiyomaru
Author-email: h.kiyomaru@gmail.com
Requires-Python: >=3.8,<4.0
Classifier: License :: OSI Approved :: BSD License
Classifier: Programming Language :: Python :: 3
Classifier: Programming Language :: Python :: 3.10
Classifier: Programming Language :: Python :: 3.6
Classifier: Programming Language :: Python :: 3.7
Classifier: Programming Language :: Python :: 3.8
Classifier: Programming Language :: Python :: 3.9
Requires-Dist: graphviz (>=0.16,<1.0.0)
Requires-Dist: pyknp (>=0.5.0,<1.0.0)
Project-URL: Documentation, https://pyknp-eventgraph.readthedocs.io/en/latest/
Project-URL: Repository, https://github.com/ku-nlp/pyknp-eventgraph
